alpha/datasets/__init__.py
alpha/datasets/enums.py
alpha/datasets/loader.py
alpha/datasets/storage.py
alpha_isnow-0.1.10.data/data/CHANGELOG.md
alpha_isnow-0.1.10.data/data/LICENSE
alpha_isnow-0.1.10.data/data/README.md
alpha_isnow-0.1.10.dist-info/licenses/LICENSE
alpha_isnow-0.1.10.dist-info/METADATA
alpha_isnow-0.1.10.dist-info/WHEEL
alpha_isnow-0.1.10.dist-info/top_level.txt
alpha_isnow-0.1.10.dist-info/RECORD
